scient/__init__.py
scient/calc_expr.cp312-win_amd64.pyd
scient/process.cp312-win_amd64.pyd
scient/service.cp312-win_amd64.pyd
scient/algorithm/__init__.py
scient/algorithm/binning.cp312-win_amd64.pyd
scient/algorithm/bktree.cp312-win_amd64.pyd
scient/algorithm/correlate.cp312-win_amd64.pyd
scient/algorithm/distance.cp312-win_amd64.pyd
scient/algorithm/entropy.cp312-win_amd64.pyd
scient/algorithm/gene.cp312-win_amd64.pyd
scient/algorithm/kdtree.cp312-win_amd64.pyd
scient/algorithm/linear_regression.cp312-win_amd64.pyd
scient/algorithm/metric.cp312-win_amd64.pyd
scient/algorithm/pca.cp312-win_amd64.pyd
scient/algorithm/similar.cp312-win_amd64.pyd
scient/algorithm/trie.cp312-win_amd64.pyd
scient/algorithm/weight.cp312-win_amd64.pyd
scient/associate/__init__.py
scient/associate/apriori.cp312-win_amd64.pyd
scient/associate/rule_merge.cp312-win_amd64.pyd
scient/associate/sbar.cp312-win_amd64.pyd
scient/cluster/__init__.py
scient/cluster/bestkmeans.cp312-win_amd64.pyd
scient/cluster/fourstep.cp312-win_amd64.pyd
scient/cluster/seqsim.cp312-win_amd64.pyd
scient/data/brand.json
scient/data/division.json
scient/data/ethnic.json
scient/data/trade.json
scient/graph/__init__.py
scient/graph/louvain.cp312-win_amd64.pyd
scient/image/__init__.py
scient/image/blend.cp312-win_amd64.pyd
scient/image/contour.cp312-win_amd64.pyd
scient/image/dedup.cp312-win_amd64.pyd
scient/image/edge.cp312-win_amd64.pyd
scient/image/feature.cp312-win_amd64.pyd
scient/image/friqa.cp312-win_amd64.pyd
scient/image/hash.cp312-win_amd64.pyd
scient/image/kernel.cp312-win_amd64.pyd
scient/image/pool.cp312-win_amd64.pyd
scient/image/process.cp312-win_amd64.pyd
scient/image/sift.cp312-win_amd64.pyd
scient/image/threshold.cp312-win_amd64.pyd
scient/language/__init__.py
scient/language/cut.cp312-win_amd64.pyd
scient/language/document.cp312-win_amd64.pyd
scient/language/entity.cp312-win_amd64.pyd
scient/language/hash.cp312-win_amd64.pyd
scient/language/keyword.cp312-win_amd64.pyd
scient-0.11.0.dist-info/METADATA
scient-0.11.0.dist-info/WHEEL
scient-0.11.0.dist-info/top_level.txt
scient-0.11.0.dist-info/RECORD
