Metadata-Version: 2.1
Name: scient
Version: 0.11.0
Summary: A python package about science compute algorithm, include natural language, image, neural network, optimize algorithm, machine learning, graphic algorithm, etc.
Author: scient
Author-email: yaomsn@live.cn
Keywords: science compute,image,natural language,machine learning,neural network,optimize algorithm,graphic algorithm
Platform: any
Requires-Python: >=3.10
Requires-Dist: numpy <2.0.0,>=1.24.0
Requires-Dist: scipy >=1.12.0
